kusa2mcap/__init__.py
kusa2mcap/cli.py
kusa2mcap-0.4.0.dist-info/METADATA
kusa2mcap-0.4.0.dist-info/WHEEL
kusa2mcap-0.4.0.dist-info/entry_points.txt
kusa2mcap-0.4.0.dist-info/top_level.txt
kusa2mcap-0.4.0.dist-info/RECORD
