Metadata-Version: 2.1
Name: kusa2mcap
Version: 0.4.0
Summary: Convert Kusa record files to MCAP format
Author-email: Lin Hai <hai.l@kusaauto.com>
License: MIT
Project-URL: Homepage, https://github.com/kusa_ads/kusa2mcap
Classifier: Programming Language :: Python :: 3
Classifier: License :: OSI Approved :: MIT License
Classifier: Operating System :: OS Independent
Requires-Python: >=3.8
Requires-Dist: click>=8.0
Requires-Dist: protobuf>=4.0
Requires-Dist: mcap-protobuf-support>=0.1.0
Requires-Dist: foxglove-schemas-protobuf>=0.1.0
Requires-Dist: kusa-ads-protobuf>=0.1.0
